{
    "display": {
    "icon": {
        "id": "minecraft:glow_item_frame"
    },
    "title": {
        "text": "Damage Level 2"
    },
    "description": {
        "text": "Boost base damage with +1",
        "color": "white",
        "italic": false
    },
    "frame": "challenge",
    "show_toast": true,
    "announce_to_chat": true,
    "hidden": false
},
"parent": "blob:stats/damage/stats_damage_1",
"criteria": {
    "root": {
        "trigger": "impossible"
    }
}
}